CHANGES.rst
MANIFEST.in
README
README.rst
setup.py
src/seven/__init__.py
src/seven/exceptions.py
src/seven/hook.py
src/seven/hook.txt
src/seven/refactor.py
src/seven/refactor.txt
src/seven/tests.py
src/seven.egg-info/PKG-INFO
src/seven.egg-info/SOURCES.txt
src/seven.egg-info/dependency_links.txt
src/seven.egg-info/namespace_packages.txt
src/seven.egg-info/requires.txt
src/seven.egg-info/top_level.txt
src/seven.egg-info/zip-safe
src/seven/fixes/__init__.py
src/seven/fixes/fix_absolute_import.py
src/seven/fixes/fix_class_decorators.py
src/seven/fixes/fix_division.py
src/seven/fixes/fix_with_statement.py
src/seven/lib2to3/Grammar.txt
src/seven/lib2to3/PatternGrammar.txt
src/seven/lib2to3/__init__.py
src/seven/lib2to3/btm_matcher.py
src/seven/lib2to3/btm_utils.py
src/seven/lib2to3/fixer_base.py
src/seven/lib2to3/fixer_util.py
src/seven/lib2to3/main.py
src/seven/lib2to3/patcomp.py
src/seven/lib2to3/pygram.py
src/seven/lib2to3/pytree.py
src/seven/lib2to3/refactor.py
src/seven/lib2to3/pgen2/__init__.py
src/seven/lib2to3/pgen2/driver.py
src/seven/lib2to3/pgen2/grammar.py
src/seven/lib2to3/pgen2/literals.py
src/seven/lib2to3/pgen2/parse.py
src/seven/lib2to3/pgen2/pgen.py
src/seven/lib2to3/pgen2/token.py
src/seven/lib2to3/pgen2/tokenize.py
src/seven/test/__init__.py
src/seven/test/class_decorators.py
src/seven/test/division.py
src/seven/test/with_statement.py
src/seven/test/absolute_import/__init__.py
src/seven/test/absolute_import/os.py
src/seven/test/absolute_import/test.py