Metadata-Version: 1.1
Name: seven
Version: 1.0.0
Summary: Python 2.5 compatibility wrapper for Python 2.7 code.
Home-page: http://github.com/aatiis/seven
Author: Attila Olah
Author-email: attilaolah@gmail.com
License: PSF License
Platform: UNKNOWN
Classifier: Development Status :: 4 - Beta
Classifier: Framework :: Buildout
Classifier: Intended Audience :: Developers
Classifier: License :: OSI Approved
Classifier: License :: OSI Approved :: MIT License
Classifier: License :: OSI Approved :: Python Software Foundation License
Classifier: Operating System :: OS Independent
Classifier: Programming Language :: Python
Classifier: Programming Language :: Python :: 2
Classifier: Programming Language :: Python :: 2.5
Classifier: Programming Language :: Python :: 2.6
Classifier: Programming Language :: Python :: 2.7
Classifier: Topic :: Software Development
Classifier: Topic :: Software Development :: Code Generators
Classifier: Topic :: Software Development :: Libraries
Classifier: Topic :: Software Development :: Libraries :: Python Modules
